ocel/__init__.py
ocel/interface.py
ocel/exporter/__init__.py
ocel/exporter/exporter.py
ocel/exporter/oceljson.py
ocel/exporter/ocelxml.py
ocel/importer/__init__.py
ocel/importer/importer.py
ocel/importer/oceljson.py
ocel/importer/ocelxml.py
ocel/validation/__init__.py
ocel/validation/oceljson.py
ocel/validation/ocelxml.py
ocel/validation/validate.py
ocel_standard-0.0.3.1.dist-info/LICENSE
ocel_standard-0.0.3.1.dist-info/METADATA
ocel_standard-0.0.3.1.dist-info/WHEEL
ocel_standard-0.0.3.1.dist-info/top_level.txt
ocel_standard-0.0.3.1.dist-info/RECORD
