Metadata-Version: 2.1
Name: ocel-standard
Version: 0.0.3.1
Summary: OCEL (object-centric event log) support for Python
Home-page: http://www.pm4py.org
Author: PADS
Author-email: a.berti@pads.rwth-aachen.de
License: GPL-3.0
Platform: UNKNOWN
Requires-Dist: jsonschema
Requires-Dist: lxml
